.gitignore
.readthedocs.yml
.travis.yml
LICENSE
MANIFEST.in
README.md
requirements.txt
setup.cfg
setup.py
styleguide.txt
RGT.egg-info/PKG-INFO
RGT.egg-info/SOURCES.txt
RGT.egg-info/dependency_links.txt
RGT.egg-info/entry_points.txt
RGT.egg-info/requires.txt
RGT.egg-info/top_level.txt
c/Makefile
c/librgt.c
c/librgt.h
c/librgt.so
c/test_librgt/viactypes.py
data/setupBinaries.py
data/setupGenomicData.py
data/setupLogoData.py
data/bin/linux/bedGraphToBigWig
data/bin/linux/bedToBigBed
data/bin/linux/bigBedToBed
data/bin/linux/bigWigMerge
data/bin/linux/wigToBigWig
data/bin/mac/bedGraphToBigWig
data/bin/mac/bedToBigBed
data/bin/mac/bigBedToBed
data/bin/mac/bigWigMerge
data/bin/mac/wigToBigWig
data/bt8/alias_bt8.txt
data/bt8/chrom.sizes.bt8
data/bt8/genes_bt8.bed
data/examples/AnnotationSet.py
data/fig/default_motif_logo.png
data/fig/jquery-1.11.1.js
data/fig/jquery.tablesorter.min.js
data/fig/rgt_logo.gif
data/fig/style.css
data/fig/tdf_logo.png
data/fig/viz_logo.png
data/fp_hmms/H3K4me3_proximal.hmm
data/fp_hmms/atac_bias_table_F.txt
data/fp_hmms/atac_bias_table_R.txt
data/fp_hmms/atac_histone.hmm
data/fp_hmms/atac_histone_bc.hmm
data/fp_hmms/atac_paired.pkl
data/fp_hmms/atac_single.pkl
data/fp_hmms/dnase.hmm
data/fp_hmms/dnase_bc.hmm
data/fp_hmms/dnase_histone.hmm
data/fp_hmms/dnase_histone_bc.hmm
data/fp_hmms/double_hit_bias_table_F.txt
data/fp_hmms/double_hit_bias_table_R.txt
data/fp_hmms/histone.hmm
data/fp_hmms/single_hit_bias_table_F.txt
data/fp_hmms/single_hit_bias_table_R.txt
data/fp_hmms/test.fa
data/hg19/alias_human.txt
data/hg19/chrom.sizes.hg19
data/hg19/genes_Gencode_hg19.bed
data/hg19/genes_RefSeq_hg19.bed
data/hg38/alias_human.txt
data/hg38/chrom.sizes.hg38
data/hg38/genes_Gencode_hg38.bed
data/hg38/genes_RefSeq_hg38.bed
data/lib/librgt_linux.so
data/lib/librgt_mac.so
data/lib/librgt_mac_arm64.so
data/lib/libtriplexator.dylib
data/lib/libtriplexator.so
data/mm10/alias_mouse.txt
data/mm10/chrom.sizes.mm10
data/mm10/genes_Gencode_mm10.bed
data/mm10/genes_RefSeq_mm10.bed
data/mm39/alias_mouse.txt
data/mm39/chrom.sizes.mm39
data/mm39/genes_Gencode_mm39.bed
data/mm9/alias_mouse.txt
data/mm9/chrom.sizes.mm9
